algop/__init__.py
algop-0.0.6.dist-info/LICENSE
algop-0.0.6.dist-info/METADATA
algop-0.0.6.dist-info/WHEEL
algop-0.0.6.dist-info/top_level.txt
algop-0.0.6.dist-info/RECORD
