Metadata-Version: 2.1
Name: algop
Version: 0.0.6
Summary: Common Algorithms
Home-page: https://github.com/isahaji/algop
Author: Isa Haji
Author-email: isa@isahaji.com
License: UNKNOWN
Project-URL: Bug Tracker, https://github.com/isahaji/algop/issues
Platform: UNKNOWN
Classifier: Programming Language :: Python :: 3
Classifier: License :: OSI Approved :: MIT License
Classifier: Operating System :: OS Independent
Requires-Python: >=3.6
License-File: LICENSE
